Workbook

Sheet Assumptions
A1: PROJECT QUARTZ — Licence Royalty Model
A2: Aldridge Biomaterials Limited — executed terms (12 December 2025)
A4: Assumption | B4: Value
A5: Upfront fee (£) | B5: 1250000
A6: Running royalty rate | B6: 0.05
A7: Royalty rate (term sheet, superseded) | B7: 0.065
A8: Min. annual royalty — Year 1 (£) | B8: 150000
A9: Min. annual royalty — Year 2 (£) | B9: 350000
A10: Min. annual royalty — Year 3+ (£) | B10: 500000
A11: Net Sales — Year 1 forecast (£) | B11: 2200000
A12: Net Sales growth p.a. | B12: 0.35
A13: Discount rate (NPV) | B13: 0.12

Sheet Royalty Projection
A1: 10-Year Royalty Projection (5.0% of Net Sales, with minimum annual royalty floor)
A3: Contract year | B3: Net Sales (£) | C3: Running royalty @5.0% (£) | D3: Minimum royalty (£) | E3: Royalty payable (£) | F3: Discount factor | G3: PV of royalty (£)
A4: 1 | B4: =Assumptions!$B$11 | C4: =B4*Assumptions!$B$6 | D4: =Assumptions!$B$8 | E4: =MAX(C4,D4) | F4: =1/((1+Assumptions!$B$13)^A4) | G4: =E4*F4
A5: 2 | B5: =B4*(1+Assumptions!$B$12) | C5: =B5*Assumptions!$B$6 | D5: =Assumptions!$B$9 | E5: =MAX(C5,D5) | F5: =1/((1+Assumptions!$B$13)^A5) | G5: =E5*F5
A6: 3 | B6: =B5*(1+Assumptions!$B$12) | C6: =B6*Assumptions!$B$6 | D6: =Assumptions!$B$10 | E6: =MAX(C6,D6) | F6: =1/((1+Assumptions!$B$13)^A6) | G6: =E6*F6
A7: 4 | B7: =B6*(1+Assumptions!$B$12) | C7: =B7*Assumptions!$B$6 | D7: =Assumptions!$B$10 | E7: =MAX(C7,D7) | F7: =1/((1+Assumptions!$B$13)^A7) | G7: =E7*F7
A8: 5 | B8: =B7*(1+Assumptions!$B$12) | C8: =B8*Assumptions!$B$6 | D8: =Assumptions!$B$10 | E8: =MAX(C8,D8) | F8: =1/((1+Assumptions!$B$13)^A8) | G8: =E8*F8
A9: 6 | B9: =B8*(1+Assumptions!$B$12) | C9: =B9*Assumptions!$B$6 | D9: =Assumptions!$B$10 | E9: =MAX(C9,D9) | F9: =1/((1+Assumptions!$B$13)^A9) | G9: =E9*F9
A10: 7 | B10: =B9*(1+Assumptions!$B$12) | C10: =B10*Assumptions!$B$6 | D10: =Assumptions!$B$10 | E10: =MAX(C10,D10) | F10: =1/((1+Assumptions!$B$13)^A10) | G10: =E10*F10
A11: 8 | B11: =B10*(1+Assumptions!$B$12) | C11: =B11*Assumptions!$B$6 | D11: =Assumptions!$B$10 | E11: =MAX(C11,D11) | F11: =1/((1+Assumptions!$B$13)^A11) | G11: =E11*F11
A12: 9 | B12: =B11*(1+Assumptions!$B$12) | C12: =B12*Assumptions!$B$6 | D12: =Assumptions!$B$10 | E12: =MAX(C12,D12) | F12: =1/((1+Assumptions!$B$13)^A12) | G12: =E12*F12
A13: 10 | B13: =B12*(1+Assumptions!$B$12) | C13: =B13*Assumptions!$B$6 | D13: =Assumptions!$B$10 | E13: =MAX(C13,D13) | F13: =1/((1+Assumptions!$B$13)^A13) | G13: =E13*F13
A14: Total | C14: =SUM(C4:C13) | D14: =SUM(D4:D13) | E14: =SUM(E4:E13) | G14: =SUM(G4:G13)
A16: Upfront fee (£) | B16: =Assumptions!$B$5
A17: NPV of royalties (£) | B17: =G14
A18: Total deal value (upfront + NPV royalties) (£) | B18: =B16+B17
A20: Model reflects executed terms: 5.0% royalty, £1.25m upfront, minimum annual royalties £150k/£350k/£500k. The 6.5% term-sheet rate (Assumptions B7) was superseded in negotiation.
