Workbook

Sheet Fee Model
A1: PROJECT NORTHWIND — ROYALTY & FEE MODEL
A2: Penrose Robotics Limited (Licensor) / Wexbourne Retail Group Limited (Licensee) — Licence dated 12 January 2026
A3: All figures £ exclusive of VAT. Blue = input assumption; black = formula. Prepared by Whitfield Carter LLP.
A5: KEY ASSUMPTIONS
A7: Up-front licence fee | B7: 3200000
A8: Per-robot royalty (standard, p.a.) | B8: 1450
A9: Per-robot royalty (early adopter, first 250, p.a.) | B9: 1160
A10: Annual minimum royalty robots | B10: 750
A11: Maintenance & support (% of licence fee) | B11: 0.18
A12: CPIH indexation cap (p.a.) | B12: 0.04
A13: Escrow fees p.a. (shared 50/50) | B13: 3600
A14: Annual maintenance & support charge (derived) | B14: =B7*B11 -> 576000
A17: 5-YEAR REVENUE BUILD
A18: Contract Year | B18: Deployed Robots (peak) | C18: Std-rate robots | D18: Early-adopter robots | E18: Royalty revenue | F18: Min. royalty top-up | G18: Maintenance & support | H18: Total annual fees
A19: Year 1 | B19: 280 | C19: =MAX(0,B19-D19) -> 30 | D19: =MIN(250,B19) -> 250 | E19: =C19*$B$8+D19*$B$9 -> 333500 | F19: =MAX(0,$B$10*$B$8-E19) -> 754000 | G19: =$B$14*(1+$B$12)^0 -> 576000 | H19: =E19+F19+G19 -> 1663500
A20: Year 2 | B20: 560 | C20: =MAX(0,B20-D20) -> 310 | D20: =MIN(250,B20) -> 250 | E20: =C20*$B$8+D20*$B$9 -> 739500 | F20: =MAX(0,$B$10*$B$8-E20) -> 348000 | G20: =$B$14*(1+$B$12)^1 -> 599040 | H20: =E20+F20+G20 -> 1686540
A21: Year 3 | B21: 820 | C21: =MAX(0,B21-D21) -> 570 | D21: =MIN(250,B21) -> 250 | E21: =C21*$B$8+D21*$B$9 -> 1116500 | F21: =MAX(0,$B$10*$B$8-E21) -> 0 | G21: =$B$14*(1+$B$12)^2 -> 623001.6 | H21: =E21+F21+G21 -> 1739501.6
A22: Year 4 | B22: 1010 | C22: =MAX(0,B22-D22) -> 760 | D22: =MIN(250,B22) -> 250 | E22: =C22*$B$8+D22*$B$9 -> 1392000 | F22: =MAX(0,$B$10*$B$8-E22) -> 0 | G22: =$B$14*(1+$B$12)^3 -> 647921.66 | H22: =E22+F22+G22 -> 2039921.7
A23: Year 5 | B23: 1180 | C23: =MAX(0,B23-D23) -> 930 | D23: =MIN(250,B23) -> 250 | E23: =C23*$B$8+D23*$B$9 -> 1638500 | F23: =MAX(0,$B$10*$B$8-E23) -> 0 | G23: =$B$14*(1+$B$12)^4 -> 673838.53 | H23: =E23+F23+G23 -> 2312338.5
A24: Total (excl. up-front) | E24: =SUM(E19:E23) -> 5220000 | F24: =SUM(F19:F23) -> 1102000 | G24: =SUM(G19:G23) -> 3119801.8 | H24: =SUM(H19:H23) -> 9441801.8
A26: Up-front licence fee | H26: =B7 -> 3200000
A27: Total recurring fees (Years 1–5) | H27: =H24 -> 9441801.8
A28: Total 5-year contract value | H28: =H26+H27 -> 12641802

Sheet Quarterly Royalty
A1: QUARTERLY ROYALTY SCHEDULE — YEAR 1
A2: Royalty charged on peak Deployed Robots per quarter; reconciled to annual minimum at year end.
A4: Quarter | B4: Peak Deployed Robots | C4: Std robots | D4: Early-adopter robots | E4: Quarterly royalty | F4: Cumulative royalty | G4: Annual min (pro-rata) | H4: Top-up due
A5: Q1 | B5: 120 | C5: =MAX(0,B5-D5) -> 0 | D5: =MIN(250,B5) -> 120 | E5: =(C5*'Fee Model'!$B$8+D5*'Fee Model'!$B$9)/4 -> 34800 | F5: =E5 -> 34800 | G5: ='Fee Model'!$B$10*'Fee Model'!$B$8/4*1 -> 271875 | H5: =MAX(0,G5-F5) -> 237075
A6: Q2 | B6: 200 | C6: =MAX(0,B6-D6) -> 0 | D6: =MIN(250,B6) -> 200 | E6: =(C6*'Fee Model'!$B$8+D6*'Fee Model'!$B$9)/4 -> 58000 | F6: =F5+E6 -> 92800 | G6: ='Fee Model'!$B$10*'Fee Model'!$B$8/4*2 -> 543750 | H6: =MAX(0,G6-F6) -> 450950
A7: Q3 | B7: 250 | C7: =MAX(0,B7-D7) -> 0 | D7: =MIN(250,B7) -> 250 | E7: =(C7*'Fee Model'!$B$8+D7*'Fee Model'!$B$9)/4 -> 72500 | F7: =F6+E7 -> 165300 | G7: ='Fee Model'!$B$10*'Fee Model'!$B$8/4*3 -> 815625 | H7: =MAX(0,G7-F7) -> 650325
A8: Q4 | B8: 280 | C8: =MAX(0,B8-D8) -> 30 | D8: =MIN(250,B8) -> 250 | E8: =(C8*'Fee Model'!$B$8+D8*'Fee Model'!$B$9)/4 -> 83375 | F8: =F7+E8 -> 248675 | G8: ='Fee Model'!$B$10*'Fee Model'!$B$8/4*4 -> 1087500 | H8: =MAX(0,G8-F8) -> 838825
A9: Year 1 total | E9: =SUM(E5:E8) -> 248675
A11: Note: cross-check Q4 cumulative royalty + final top-up against Year 1 minimum royalty in Fee Model.

Sheet Patent Schedule
A1: SCHEDULE 1 — LICENSED PATENTS & MAINTENANCE COST INDEX
A2: Patents and applications licensed under the Northwind licence; annual renewal/maintenance cost borne by Licensor (cl. 7.3).
A4: No. | B4: Application / Grant No. | C4: Jurisdiction | D4: Title | E4: Status | F4: Next renewal | G4: Annual cost (£)
A5: 1 | B5: EP3 842 119 B1 | C5: EPO (UK/DE/FR/IE) | D5: Collision-free path planning in dynamic warehouse environments | E5: Granted | F5: 2027-03-31 | G5: 4200
A6: 2 | B6: GB2 597 044 B | C6: United Kingdom | D6: Multi-robot fleet orchestration via decentralised traffic negotiation | E6: Granted | F6: 2026-11-30 | G6: 650
A7: 3 | B7: US 11,512,983 B2 | C7: United States | D7: Real-time perception & obstacle classification in mobile robots | E7: Granted | F7: 2028-01-15 | G7: 3100
A8: 4 | B8: EP21 198 776.2 | C8: EPO (pending) | D8: Adaptive charging & task scheduling for AMR fleets | E8: Pending | F8: 2026-09-30 | G8: 2800
A9: 5 | B9: GB2 611 902 A | C9: United Kingdom | D9: Dynamic re-routing on detection of human co-workers | E9: Under exam. | F9: 2026-08-31 | G9: 900
D10: Total annual portfolio maintenance cost | G10: =SUM(G5:G9) -> 11650
