Workbook

Sheet Assumptions
A1: Project Lyra — Patent & Know-How Licence: Royalty & Value Model
A2: Veridian Photonics Limited (Licensor) / Marrick Defence Systems plc (Licensee)
A3: Execution version dated 27 June 2025. Figures consistent with the executed Licence.
A5: Key commercial terms
A6: Upfront fee (clause 5.1) | B6: 4500000
A7: Milestone — total (clause 5.2) | B7: 2000000
A8: Milestone tranche 1 (on first sale) | B8: =B7/2
A9: Milestone tranche 2 (1st anniv. of first sale) | B9: =B7/2
A10: Running royalty rate (clause 5.3) | B10: 0.06
A11: Minimum annual royalty from Yr 3 (clause 5.4) | B11: 750000
A12: Audit underpayment threshold (clause 5.7) | B12: 0.05
A13: Discount rate (Veridian internal, for NPV) | B13: 0.12
A14: First commercial sale (months from Effective Date) | B14: 22
A16: Inputs in blue / yellow are assumptions; black are formulas; green link to other sheets.

Sheet Royalty Projection
A1: Net Sales & Royalty Projection (Years 1–6 from Effective Date)
A2: Year 1 reflects part-year sales (first commercial sale at month 22).
A4: Line item | B4: Year 1 | C4: Year 2 | D4: Year 3 | E4: Year 4 | F4: Year 5 | G4: Year 6 | H4: Total
A5: Units sold (systems) | B5: 130 | C5: 660 | D5: 1200 | E5: 1660 | F5: 2025 | G5: 2205 | H5: =SUM(B5:G5)
A6: Average selling price (£) | B6: 185000 | C6: 185000 | D6: 185000 | E6: 185000 | F6: 185000 | G6: 185000 | H6: =SUM(B6:G6)
A7: Net Sales (£) | B7: =B5*B6 | C7: =C5*C6 | D7: =D5*D6 | E7: =E5*E6 | F7: =F5*F6 | G7: =G5*G6 | H7: =SUM(B7:G7)
A8: Running royalty @ rate | B8: =B7*Assumptions!$B$10 | C8: =C7*Assumptions!$B$10 | D8: =D7*Assumptions!$B$10 | E8: =E7*Assumptions!$B$10 | F8: =F7*Assumptions!$B$10 | G8: =G7*Assumptions!$B$10 | H8: =SUM(B8:G8)
A9: Minimum-royalty top-up (Yr 3+) | B9: 0 | C9: 0 | D9: =MAX(0,Assumptions!$B$11-D8) | E9: =MAX(0,Assumptions!$B$11-E8) | F9: =MAX(0,Assumptions!$B$11-F8) | G9: =MAX(0,Assumptions!$B$11-G8) | H9: =SUM(B9:G9)
A10: Royalty payable to Veridian | B10: =MAX(B8,B8+B9) | C10: =MAX(C8,C8+C9) | D10: =MAX(D8,D8+D9) | E10: =MAX(E8,E8+E9) | F10: =MAX(F8,F8+F9) | G10: =MAX(G8,G8+G9) | H10: =SUM(B10:G10)
A12: One-off receipts
A13: Upfront fee | B13: =Assumptions!$B$6 | C13: 0 | D13: 0 | E13: 0 | F13: 0 | G13: 0 | H13: =SUM(B13:G13)
A14: Milestone tranche 1 | B14: =Assumptions!$B$8 | C14: 0 | D14: 0 | E14: 0 | F14: 0 | G14: 0 | H14: =SUM(B14:G14)
A15: Milestone tranche 2 | B15: 0 | C15: =Assumptions!$B$9 | D15: 0 | E15: 0 | F15: 0 | G15: 0 | H15: =SUM(B15:G15)
A16: Total cash to Veridian | B16: =B10+B13+B14+B15 | C16: =C10+C13+C14+C15 | D16: =D10+D13+D14+D15 | E16: =E10+E13+E14+E15 | F16: =F10+F13+F14+F15 | G16: =G10+G13+G14+G15 | H16: =SUM(B16:G16)
A18: NPV of total cash to Veridian @ discount rate | B18: =NPV(Assumptions!$B$13,B16:G16)
A19: Cumulative royalties (Years 1–6) | B19: =H10
A20: Cumulative total receipts (Years 1–6) | B20: =H16

Sheet Royalty Sensitivity
A1: Year-6 royalty sensitivity (rate x units)
A3: Royalty rate \ Year-6 units
B4: 1800 | C4: 2000 | D4: 2150 | E4: 2400
A5: 0.0575 | B5: =1800*'Royalty Projection'!$G$6*$A5 | C5: =2000*'Royalty Projection'!$G$6*$A5 | D5: =2150*'Royalty Projection'!$G$6*$A5 | E5: =2400*'Royalty Projection'!$G$6*$A5
A6: 0.06 | B6: =1800*'Royalty Projection'!$G$6*$A6 | C6: =2000*'Royalty Projection'!$G$6*$A6 | D6: =2150*'Royalty Projection'!$G$6*$A6 | E6: =2400*'Royalty Projection'!$G$6*$A6
A7: 0.065 | B7: =1800*'Royalty Projection'!$G$6*$A7 | C7: =2000*'Royalty Projection'!$G$6*$A7 | D7: =2150*'Royalty Projection'!$G$6*$A7 | E7: =2400*'Royalty Projection'!$G$6*$A7
A10: ASP held at the projection Year-6 value. Base case (executed): 6.0% rate, 2,150 units.
