Workbook

Sheet Assumptions
A1: Project Cedar — Royalty Model: Assumptions
A2: Larkmoor Bioscience Limited (Licensor) / Verrell Beauty Group plc (Licensee). All figures £ unless stated. Blue = input.
A4: Key commercial terms (per executed Licence Agreement dated 19 January 2026)
A5: Upfront fee | B5: 1750000 | C5: Clause 7.1
A6: Running royalty rate (Valid Claim) | B6: 0.055 | C6: Clause 7.3 (as negotiated, v3)
A7: Know-how-only royalty rate | B7: 0.04 | C7: Clause 7.4
A8: Net Sales milestone trigger | B8: 25000000 | C8: Schedule 4 Part B
A9: Aggregate milestone cap | B9: 4250000 | C9: Schedule 4 Part B
A10: Minimum annual royalty — Year 2 | B10: 150000 | C10: Schedule 4 Part D
A11: Minimum annual royalty — Year 3 | B11: 350000 | C11: Schedule 4 Part D
A12: Minimum annual royalty — Year 4+ | B12: 600000 | C12: Schedule 4 Part D
A13: VAT rate (for reference) | B13: 0.2 | C13: Clause 8.2

Sheet Net Sales & Royalty
A1: Project Cedar — Net Sales & Royalty Projection (illustrative)
A2: 10 contract years from first commercial sale. Net Sales split into Valid-Claim and Know-How-only baskets. Green = link to Assumptions.
A4: £ unless stated | B4: Year 1 | C4: Year 2 | D4: Year 3 | E4: Year 4 | F4: Year 5 | G4: Year 6 | H4: Year 7 | I4: Year 8 | J4: Year 9 | K4: Year 10 | L4: Total / 10 yrs
A5: Net Sales — Valid-Claim products | B5: 0 | C5: 2200000 | D5: 6800000 | E5: 14500000 | F5: 23000000 | G5: 31000000 | H5: 38000000 | I5: 44000000 | J5: 49000000 | K5: 53000000 | L5: =SUM(B5:K5) -> 261500000
A6: Net Sales — Know-How-only products | B6: 0 | C6: 300000 | D6: 1100000 | E6: 2600000 | F6: 4200000 | G6: 5500000 | H6: 6800000 | I6: 7600000 | J6: 8200000 | K6: 8700000 | L6: =SUM(B6:K6) -> 45000000
A7: Total Net Sales | B7: =B5+B6 -> 0 | C7: =C5+C6 -> 2500000 | D7: =D5+D6 -> 7900000 | E7: =E5+E6 -> 17100000 | F7: =F5+F6 -> 27200000 | G7: =G5+G6 -> 36500000 | H7: =H5+H6 -> 44800000 | I7: =I5+I6 -> 51600000 | ... K7: =K5+K6 -> 61700000 | L7: =SUM(B7:K7) -> 306500000
A8: Royalty on Valid-Claim sales (5.5%) | B8: =B5*Assumptions!$B$6 -> 0 | C8: =C5*Assumptions!$B$6 -> 121000 | D8: =D5*Assumptions!$B$6 -> 374000 | E8: =E5*Assumptions!$B$6 -> 797500 | F8: =F5*Assumptions!$B$6 -> 1265000 | G8: =G5*Assumptions!$B$6 -> 1705000 | H8: =H5*Assumptions!$B$6 -> 2090000 | I8: =I5*Assumptions!$B$6 -> 2420000 | ... K8: =K5*Assumptions!$B$6 -> 2915000 | L8: =SUM(B8:K8) -> 14382500
A9: Royalty on Know-How sales (4.0%) | B9: =B6*Assumptions!$B$7 -> 0 | C9: =C6*Assumptions!$B$7 -> 12000 | D9: =D6*Assumptions!$B$7 -> 44000 | E9: =E6*Assumptions!$B$7 -> 104000 | F9: =F6*Assumptions!$B$7 -> 168000 | G9: =G6*Assumptions!$B$7 -> 220000 | H9: =H6*Assumptions!$B$7 -> 272000 | I9: =I6*Assumptions!$B$7 -> 304000 | ... K9: =K6*Assumptions!$B$7 -> 348000 | L9: =SUM(B9:K9) -> 1800000
A10: Earned royalty (subtotal) | B10: =B8+B9 -> 0 | C10: =C8+C9 -> 133000 | D10: =D8+D9 -> 418000 | E10: =E8+E9 -> 901500 | F10: =F8+F9 -> 1433000 | G10: =G8+G9 -> 1925000 | H10: =H8+H9 -> 2362000 | I10: =I8+I9 -> 2724000 | ... K10: =K8+K9 -> 3263000 | L10: =SUM(B10:K10) -> 16182500
A11: Minimum annual royalty | B11: 0 | C11: =Assumptions!$B$10 -> 150000 | D11: =Assumptions!$B$11 -> 350000 | E11: =Assumptions!$B$12 -> 600000 | F11: =Assumptions!$B$12 -> 600000 | G11: =Assumptions!$B$12 -> 600000 | H11: =Assumptions!$B$12 -> 600000 | I11: =Assumptions!$B$12 -> 600000 | J11: =Assumptions!$B$12 -> 600000 | K11: =Assumptions!$B$12 -> 600000
A12: Royalty payable (greater of earned / minimum) | B12: =MAX(B10,B11) -> 0 | C12: =MAX(C10,C11) -> 150000 | D12: =MAX(D10,D11) -> 418000 | E12: =MAX(E10,E11) -> 901500 | F12: =MAX(F10,F11) -> 1433000 | G12: =MAX(G10,G11) -> 1925000 | H12: =MAX(H10,H11) -> 2362000 | I12: =MAX(I10,I11) -> 2724000 | ... K12: =MAX(K10,K11) -> 3263000 | L12: =SUM(B12:K12) -> 16199500
A13: Cumulative royalty payable | B13: =B12 -> 0 | C13: =B13+C12 -> 150000 | D13: =C13+D12 -> 568000 | E13: =D13+E12 -> 1469500 | F13: =E13+F12 -> 2902500 | G13: =F13+G12 -> 4827500 | H13: =G13+H12 -> 7189500 | I13: =H13+I12 -> 9913500 | J13: =I13+J12 -> 12936500 | K13: =J13+K12 -> 16199500
A14: Effective royalty rate (% of Net Sales) | B14: =IF(B7=0,0,B12/B7) -> 0 | C14: =IF(C7=0,0,C12/C7) -> 0.06 | D14: =IF(D7=0,0,D12/D7) -> 0.052911392 | E14: =IF(E7=0,0,E12/E7) -> 0.052719298 | F14: =IF(F7=0,0,F12/F7) -> 0.052683824 | G14: =IF(G7=0,0,G12/G7) -> 0.052739726 | H14: =IF(H7=0,0,H12/H7) -> 0.052723214 | I14: =IF(I7=0,0,I12/I7) -> 0.052790698 | ... K14: =IF(K7=0,0,K12/K7) -> 0.052884927
A16: Note: illustrative projection prepared for internal modelling only; Net Sales inputs are estimates. Royalty payable reflects the minimum-annual-royalty floor (Clause 7.6) and the negotiated 5.5% rate (Clause 7.3).

Sheet Deal Summary
A1: Project Cedar — Total Consideration Summary
A2: Upfront + milestones + 10-year royalty (illustrative).
A4: Component | B4: Amount (£) | C4: Reference
A5: Upfront fee | B5: =Assumptions!B5 -> 1750000 | C5: Clause 7.1
A6: Milestone payments (max, if all achieved) | B6: =Assumptions!B9 -> 4250000 | C6: Schedule 4 Part B
A7: Royalties — 10-year illustrative total | B7: ='Net Sales & Royalty'!L12 -> 16199500 | C7: Net Sales & Royalty sheet
A8: Total illustrative consideration | B8: =SUM(B5:B7) -> 22199500
