Workbook

Sheet Pricing Schedule
A1: Harrow Precision Engineering — Stratton Energy plc
A2: Supply Agreement WC-00150 — Pricing & Volume Model (Schedule 3)
A3: Prepared by Whitfield Carter LLP — fixed Year 1; annual index review capped at 4%. All figures ex VAT.
A5: Part No. | B5: Product | C5: Unit list price (£) | D5: Vol. disc. tier 1 (5%) | E5: Tier 2 (8%) | F5: Tier 3 (11%)
A6: HX-150-CW | B6: HX-Series end-suction pump 150mm | C6: 18400 | D6: =C6*(1-0.05) -> 17480 | E6: =C6*(1-0.08) -> 16928 | F6: =C6*(1-0.11) -> 16376
A7: HX-200-BP | B7: HX-Series packaged booster set 200mm | C7: 42750 | D7: =C7*(1-0.05) -> 40612.5 | E7: =C7*(1-0.08) -> 39330 | F7: =C7*(1-0.11) -> 38047.5
A8: HX-300-PS | B8: HX-Series split-case process pump 300mm | C8: 67500 | D8: =C8*(1-0.05) -> 64125 | E8: =C8*(1-0.08) -> 62100 | F8: =C8*(1-0.11) -> 60075
A9: HX-SEAL-K | B9: Mechanical seal cartridge kit | C9: 2150 | D9: =C9*(1-0.05) -> 2042.5 | E9: =C9*(1-0.08) -> 1978 | F9: =C9*(1-0.11) -> 1913.5
A12: Volume discount tiers (aggregate annual order value, ex VAT)
A13: Tier | B13: Lower (£) | C13: Upper (£) | D13: Discount
A14: 1 (up to commitment) | B14: 0 | C14: 3200000 | D14: 0.05
A15: 2 | B15: 3200001 | C15: 5000000 | D15: 0.08
A16: 3 (over £5m) | B16: 5000001 | C16: 99999999 | D16: 0.11

Sheet Annual Spend Projection
A1: 5-Year Spend Projection vs Minimum Purchase Commitment
A2: Minimum Purchase Commitment (clause 4): £3,200,000 / Contract Year. Shortfall payment 15% of any under-delivery.
A4: Assumptions
A5: Minimum Purchase Commitment (£/yr) | B5: 3200000
A6: Shortfall payment rate | B6: 0.15
A7: Annual price index cap | B7: 0.04
A9: Contract Year | B9: Forecast order value (£) | C9: Min. commitment (£) | D9: Shortfall vs commitment (£) | E9: Shortfall payment due (£) | F9: Cum. spend (£)
A10: Year 1 | B10: 3050000 | C10: =$B$5 -> 3200000 | D10: =MAX(0,C10-B10) -> 150000 | E10: =D10*$B$6 -> 22500 | F10: =B10 -> 3050000
A11: Year 2 | B11: 3400000 | C11: =$B$5 -> 3200000 | D11: =MAX(0,C11-B11) -> 0 | E11: =D11*$B$6 -> 0 | F11: =F10+B11 -> 6450000
A12: Year 3 | B12: 3650000 | C12: =$B$5 -> 3200000 | D12: =MAX(0,C12-B12) -> 0 | E12: =D12*$B$6 -> 0 | F12: =F11+B12 -> 10100000
A13: Year 4 | B13: 3900000 | C13: =$B$5 -> 3200000 | D13: =MAX(0,C13-B13) -> 0 | E13: =D13*$B$6 -> 0 | F13: =F12+B13 -> 14000000
A14: Year 5 | B14: 4250000 | C14: =$B$5 -> 3200000 | D14: =MAX(0,C14-B14) -> 0 | E14: =D14*$B$6 -> 0 | F14: =F13+B14 -> 18250000
A15: Total / Cap status | B15: =SUM(B10:B14) -> 18250000 | E15: =SUM(E10:E14) -> 22500

Sheet Liability Cap
A1: Liability Cap Illustration (clause 11.3 — executed: 125% of trailing 12m charges)
A3: Executed general cap % | B3: 1.25
A4: Executed IP indemnity sub-cap % | B4: 2
A5: LDs for late delivery (count towards cap?) | B5: Yes — within cap
A7: Contract Year | B7: Charges paid trailing 12m (£) | C7: General liability cap (£) | D7: IP indemnity sub-cap (£)
A8: Year 1 | B8: ='Annual Spend Projection'!B10 -> 3050000 | C8: =B8*$B$3 -> 3812500 | D8: =B8*$B$4 -> 6100000
A9: Year 2 | B9: ='Annual Spend Projection'!B11 -> 3400000 | C9: =B9*$B$3 -> 4250000 | D9: =B9*$B$4 -> 6800000
A10: Year 3 | B10: ='Annual Spend Projection'!B12 -> 3650000 | C10: =B10*$B$3 -> 4562500 | D10: =B10*$B$4 -> 7300000
A11: Year 4 | B11: ='Annual Spend Projection'!B13 -> 3900000 | C11: =B11*$B$3 -> 4875000 | D11: =B11*$B$4 -> 7800000
A12: Year 5 | B12: ='Annual Spend Projection'!B14 -> 4250000 | C12: =B12*$B$3 -> 5312500 | D12: =B12*$B$4 -> 8500000
