Workbook

Sheet Assumptions
A1: Project Yarrow — Pricing Model
A2: Halstead Aerospace Limited / Caldera Mobility Systems plc — CMS-1 Skylark composite airframe structures
A3: Basis: LTSA Schedule 3 (Year-1 Unit Prices), Schedule 2 (volumes), clause 8.4 (escalation). All figures £ ex-VAT.
A4: Assumptions | B4: Value | C4: Source
A5: Year-1 unit prices (£)
A6: Y-101 Forward fuselage barrel | B6: 96500 | C6: LTSA Sch.3
A7: Y-102 Centre wing box | B7: 88200 | C7: LTSA Sch.3
A8: Y-103 Outboard wing assy — LH | B8: 47400 | C8: LTSA Sch.3
A9: Y-104 Outboard wing assy — RH | B9: 47400 | C9: LTSA Sch.3
A10: Escalation: % of CPI applied | B10: 0.8 | C10: clause 8.4
A11: Assumed CPI (annual) | B11: 0.031 | C11: planning assumption
A12: Escalation cap (per year) | B12: 0.05 | C12: clause 8.4 (final)
A13: Escalation floor | B13: 0 | C13: clause 8.4
A14: Volume rebate threshold (Ship-sets/yr) | B14: 90 | C14: clause 8.3
A15: Volume rebate rate | B15: 0.02 | C15: clause 8.3
A16: Shortfall charge rate | B16: 0.2 | C16: Sch.2 (final)
A18: Ship-set price (Year 1) | B18: =B6+B7+B8+B9 -> 279500

Sheet Revenue Build
A1: Revenue build-up by Contract Year (£ ex-VAT)
A3: Line | B3: Year 1 | C3: Year 2 | D3: Year 3 | E3: Year 4 | F3: Year 5 | G3: Year 6 | H3: Year 7 | I3: Total
A4: Planning forecast (Ship-sets) | B4: 30 | C4: 55 | D4: 80 | E4: 90 | F4: 95 | G4: 95 | H4: 95 | I4: =SUM(B4:H4) -> 540
A5: Minimum volume commitment | B5: 24 | C5: 42 | D5: 60 | E5: 72 | F5: 75 | G5: 72 | H5: 72 | I5: =SUM(B5:H5) -> 417
A6: Ship-set price (£, escalated) | B6: =Assumptions!B18 -> 279500 | C6: =B6*(1+MIN(Assumptions!$B$11,MAX(Assumptions!$B$12,Assumptions!$B$10*Assumptions!$B$11))) -> 288164.5 | D6: =C6*(1+MIN(Assumptions!$B$11,MAX(Assumptions!$B$12,Assumptions!$B$10*Assumptions!$B$11))) -> 297097.6 | E6: =D6*(1+MIN(Assumptions!$B$11,MAX(Assumptions!$B$12,Assumptions!$B$10*Assumptions!$B$11))) -> 306307.63 | F6: =E6*(1+MIN(Assumptions!$B$11,MAX(Assumptions!$B$12,Assumptions!$B$10*Assumptions!$B$11))) -> 315803.16 | G6: =F6*(1+MIN(Assumptions!$B$11,MAX(Assumptions!$B$12,Assumptions!$B$10*Assumptions!$B$11))) -> 325593.06 | H6: =G6*(1+MIN(Assumptions!$B$11,MAX(Assumptions!$B$12,Assumptions!$B$10*Assumptions!$B$11))) -> 335686.44
A7: Gross revenue (forecast) | B7: =B4*B6 -> 8385000 | C7: =C4*C6 -> 15849048 | D7: =D4*D6 -> 23767808 | E7: =E4*E6 -> 27567686 | F7: =F4*F6 -> 30001300 | G7: =G4*G6 -> 30931341 | H7: =H4*H6 -> 31890212 | I7: =SUM(B7:H7) -> 1.6839239e+08
A8: Less: volume rebate | B8: =-MAX(0,B4-Assumptions!$B$14)*B6*Assumptions!$B$15 -> 0 | C8: =-MAX(0,C4-Assumptions!$B$14)*C6*Assumptions!$B$15 -> 0 | D8: =-MAX(0,D4-Assumptions!$B$14)*D6*Assumptions!$B$15 -> 0 | E8: =-MAX(0,E4-Assumptions!$B$14)*E6*Assumptions!$B$15 -> 0 | F8: =-MAX(0,F4-Assumptions!$B$14)*F6*Assumptions!$B$15 -> -31580.316 | G8: =-MAX(0,G4-Assumptions!$B$14)*G6*Assumptions!$B$15 -> -32559.306 | H8: =-MAX(0,H4-Assumptions!$B$14)*H6*Assumptions!$B$15 -> -33568.644 | I8: =SUM(B8:H8) -> -97708.267
A9: Net revenue | B9: =B7+B8 -> 8385000 | C9: =C7+C8 -> 15849048 | D9: =D7+D8 -> 23767808 | E9: =E7+E8 -> 27567686 | F9: =F7+F8 -> 29969720 | G9: =G7+G8 -> 30898781 | H9: =H7+H8 -> 31856644 | I9: =SUM(B9:H9) -> 1.6829469e+08
A11: Aggregate contract value — escalated mid-case (net) | B11: =I9 -> 1.6829469e+08
A12: Aggregate contract value — un-escalated (Year-1 prices, net of rebate) | B12: =SUMPRODUCT($B$4:$H$4,Assumptions!$B$18-IF($B$4:$H$4>Assumptions!$B$14,(($B$4:$H$4-Assumptions!$B$14)/$B$4:$H$4)*Assumptions!$B$18*Assumptions!$B$15,0)) -> 150846150
A13: Cross-check: LTSA clause 8.2 indicative value (£148.4m, rounded) | B13: 148400000
A14: Variance (un-escalated vs clause 8.2 rounded indicative) | B14: =B12-B13 -> 2446150

Sheet Item Price Schedule
A1: Item Unit Prices by Contract Year (£ ex-VAT, escalated per clause 8.4)
A3: Item | B3: Year 1 | C3: Year 2 | D3: Year 3 | E3: Year 4 | F3: Year 5 | G3: Year 6 | H3: Year 7
A4: Y-101 Forward fuselage barrel | B4: =Assumptions!B6 -> 96500 | C4: =B4*(1+MIN(Assumptions!$B$11,MAX(Assumptions!$B$12,Assumptions!$B$10*Assumptions!$B$11))) -> 99491.5 | D4: =C4*(1+MIN(Assumptions!$B$11,MAX(Assumptions!$B$12,Assumptions!$B$10*Assumptions!$B$11))) -> 102575.74 | E4: =D4*(1+MIN(Assumptions!$B$11,MAX(Assumptions!$B$12,Assumptions!$B$10*Assumptions!$B$11))) -> 105755.58 | F4: =E4*(1+MIN(Assumptions!$B$11,MAX(Assumptions!$B$12,Assumptions!$B$10*Assumptions!$B$11))) -> 109034.01 | G4: =F4*(1+MIN(Assumptions!$B$11,MAX(Assumptions!$B$12,Assumptions!$B$10*Assumptions!$B$11))) -> 112414.06 | H4: =G4*(1+MIN(Assumptions!$B$11,MAX(Assumptions!$B$12,Assumptions!$B$10*Assumptions!$B$11))) -> 115898.9
A5: Y-102 Centre wing box | B5: =Assumptions!B7 -> 88200 | C5: =B5*(1+MIN(Assumptions!$B$11,MAX(Assumptions!$B$12,Assumptions!$B$10*Assumptions!$B$11))) -> 90934.2 | D5: =C5*(1+MIN(Assumptions!$B$11,MAX(Assumptions!$B$12,Assumptions!$B$10*Assumptions!$B$11))) -> 93753.16 | E5: =D5*(1+MIN(Assumptions!$B$11,MAX(Assumptions!$B$12,Assumptions!$B$10*Assumptions!$B$11))) -> 96659.508 | F5: =E5*(1+MIN(Assumptions!$B$11,MAX(Assumptions!$B$12,Assumptions!$B$10*Assumptions!$B$11))) -> 99655.953 | G5: =F5*(1+MIN(Assumptions!$B$11,MAX(Assumptions!$B$12,Assumptions!$B$10*Assumptions!$B$11))) -> 102745.29 | H5: =G5*(1+MIN(Assumptions!$B$11,MAX(Assumptions!$B$12,Assumptions!$B$10*Assumptions!$B$11))) -> 105930.39
A6: Y-103 Outboard wing — LH | B6: =Assumptions!B8 -> 47400 | C6: =B6*(1+MIN(Assumptions!$B$11,MAX(Assumptions!$B$12,Assumptions!$B$10*Assumptions!$B$11))) -> 48869.4 | D6: =C6*(1+MIN(Assumptions!$B$11,MAX(Assumptions!$B$12,Assumptions!$B$10*Assumptions!$B$11))) -> 50384.351 | E6: =D6*(1+MIN(Assumptions!$B$11,MAX(Assumptions!$B$12,Assumptions!$B$10*Assumptions!$B$11))) -> 51946.266 | F6: =E6*(1+MIN(Assumptions!$B$11,MAX(Assumptions!$B$12,Assumptions!$B$10*Assumptions!$B$11))) -> 53556.601 | G6: =F6*(1+MIN(Assumptions!$B$11,MAX(Assumptions!$B$12,Assumptions!$B$10*Assumptions!$B$11))) -> 55216.855 | H6: =G6*(1+MIN(Assumptions!$B$11,MAX(Assumptions!$B$12,Assumptions!$B$10*Assumptions!$B$11))) -> 56928.578
A7: Y-104 Outboard wing — RH | B7: =Assumptions!B9 -> 47400 | C7: =B7*(1+MIN(Assumptions!$B$11,MAX(Assumptions!$B$12,Assumptions!$B$10*Assumptions!$B$11))) -> 48869.4 | D7: =C7*(1+MIN(Assumptions!$B$11,MAX(Assumptions!$B$12,Assumptions!$B$10*Assumptions!$B$11))) -> 50384.351 | E7: =D7*(1+MIN(Assumptions!$B$11,MAX(Assumptions!$B$12,Assumptions!$B$10*Assumptions!$B$11))) -> 51946.266 | F7: =E7*(1+MIN(Assumptions!$B$11,MAX(Assumptions!$B$12,Assumptions!$B$10*Assumptions!$B$11))) -> 53556.601 | G7: =F7*(1+MIN(Assumptions!$B$11,MAX(Assumptions!$B$12,Assumptions!$B$10*Assumptions!$B$11))) -> 55216.855 | H7: =G7*(1+MIN(Assumptions!$B$11,MAX(Assumptions!$B$12,Assumptions!$B$10*Assumptions!$B$11))) -> 56928.578
A8: Ship-set total | B8: =SUM(B4:B7) -> 279500 | C8: =SUM(C4:C7) -> 288164.5 | D8: =SUM(D4:D7) -> 297097.6 | E8: =SUM(E4:E7) -> 306307.63 | F8: =SUM(F4:F7) -> 315803.16 | G8: =SUM(G4:G7) -> 325593.06 | H8: =SUM(H4:H7) -> 335686.44
