Workbook

Sheet Assumptions
A1: PROJECT INDIGO — DEAL ECONOMICS (ASSUMPTIONS)
A2: Cobalt Photonics / Tessandri Instruments — executed terms
A4: Assumption | B4: Value | C4: Source / note
A5: Upfront fee (£) | B5: 4500000 | C5: Cl. 6.1 — £2.0m on Effective Date + £2.5m on 1st anniversary
A6: Technology transfer fee (£) | B6: 350000 | C6: Cl. 3.2 — three instalments
A7: Running royalty rate | B7: 0.045 | C7: Cl. 6.2 — executed 4.5% of Net Sales
A8: Minimum annual royalty (£) | B8: 750000 | C8: Cl. 6.3 — from Contract Year 2
A9: Year-1 Licensee Net Sales (£) | B9: 6000000 | C9: Tessandri commercial forecast
A10: Net Sales annual growth | B10: 0.35 | C10: Ramp assumption
A11: Liability cap (% of 12m fees) | B11: 1.5 | C11: Cl. 9.3 — executed 150%

Sheet Royalty Projection
A1: 12-YEAR ROYALTY PROJECTION (£)
A3: Contract Year | B3: Net Sales | C3: Running royalty @4.5% | D3: Minimum royalty | E3: Royalty payable (greater of) | F3: Cumulative royalties
A4: 1 | B4: =Assumptions!$B$9 -> 6000000 | C4: =B4*Assumptions!$B$7 -> 270000 | D4: =0 -> 0 | E4: =MAX(C4,D4) -> 270000 | F4: =E4 -> 270000
A5: 2 | B5: =B4*(1+Assumptions!$B$10) -> 8100000 | C5: =B5*Assumptions!$B$7 -> 364500 | D5: =Assumptions!$B$8 -> 750000 | E5: =MAX(C5,D5) -> 750000 | F5: =F4+E5 -> 1020000
A6: 3 | B6: =B5*(1+Assumptions!$B$10) -> 10935000 | C6: =B6*Assumptions!$B$7 -> 492075 | D6: =Assumptions!$B$8 -> 750000 | E6: =MAX(C6,D6) -> 750000 | F6: =F5+E6 -> 1770000
A7: 4 | B7: =B6*(1+Assumptions!$B$10) -> 14762250 | C7: =B7*Assumptions!$B$7 -> 664301.25 | D7: =Assumptions!$B$8 -> 750000 | E7: =MAX(C7,D7) -> 750000 | F7: =F6+E7 -> 2520000
A8: 5 | B8: =B7*(1+Assumptions!$B$10) -> 19929038 | C8: =B8*Assumptions!$B$7 -> 896806.69 | D8: =Assumptions!$B$8 -> 750000 | E8: =MAX(C8,D8) -> 896806.69 | F8: =F7+E8 -> 3416806.7
A9: 6 | B9: =B8*(1+Assumptions!$B$10) -> 26904201 | C9: =B9*Assumptions!$B$7 -> 1210689 | D9: =Assumptions!$B$8 -> 750000 | E9: =MAX(C9,D9) -> 1210689 | F9: =F8+E9 -> 4627495.7
A10: 7 | B10: =B9*(1+Assumptions!$B$10) -> 36320671 | C10: =B10*Assumptions!$B$7 -> 1634430.2 | D10: =Assumptions!$B$8 -> 750000 | E10: =MAX(C10,D10) -> 1634430.2 | F10: =F9+E10 -> 6261925.9
A11: 8 | B11: =B10*(1+Assumptions!$B$10) -> 49032906 | C11: =B11*Assumptions!$B$7 -> 2206480.8 | D11: =Assumptions!$B$8 -> 750000 | E11: =MAX(C11,D11) -> 2206480.8 | F11: =F10+E11 -> 8468406.7
A12: 9 | B12: =B11*(1+Assumptions!$B$10) -> 66194423 | C12: =B12*Assumptions!$B$7 -> 2978749 | D12: =Assumptions!$B$8 -> 750000 | E12: =MAX(C12,D12) -> 2978749 | F12: =F11+E12 -> 11447156
A13: 10 | B13: =B12*(1+Assumptions!$B$10) -> 89362471 | C13: =B13*Assumptions!$B$7 -> 4021311.2 | D13: =Assumptions!$B$8 -> 750000 | E13: =MAX(C13,D13) -> 4021311.2 | F13: =F12+E13 -> 15468467
A14: 11 | B14: =B13*(1+Assumptions!$B$10) -> 1.2063934e+08 | C14: =B14*Assumptions!$B$7 -> 5428770.1 | D14: =Assumptions!$B$8 -> 750000 | E14: =MAX(C14,D14) -> 5428770.1 | F14: =F13+E14 -> 20897237
A15: 12 | B15: =B14*(1+Assumptions!$B$10) -> 1.628631e+08 | C15: =B15*Assumptions!$B$7 -> 7328839.6 | D15: =Assumptions!$B$8 -> 750000 | E15: =MAX(C15,D15) -> 7328839.6 | F15: =F14+E15 -> 28226077
A17: Upfront fee | E17: =Assumptions!$B$5 -> 4500000
A18: Technology transfer fee | E18: =Assumptions!$B$6 -> 350000
A19: Total royalties (12 yrs) | E19: =F15 -> 28226077
A20: Total to Licensor (12 yrs) | E20: =E17+E18+E19 -> 33076077
