Workbook

Sheet Assumptions
A1: Project Falcon - Carrowmoor BESS - Charges & Contract Value Model
A2: Verdant Energy Systems Limited (Supplier) / Stratton Energy plc (Customer)
A3: All figures GBP, excluding VAT. Executed terms (12 Feb 2026).
A5: Key assumption | B5: Value | C5: Unit / note
A6: System power rating | B6: 80 | C6: MW (input)
A7: System energy capacity | B7: 160 | C7: MWh (input)
A8: Supply price per MWh | B8: 390000 | C8: GBP/MWh (input)
A9: Supply Price (total) | B9: =B7*B8 -> 62400000 | C9: GBP = capacity (B7) x unit price (B8)
A10: Annual Licence Fee (year 1) | B10: 840000 | C10: GBP, CPI-indexed (input)
A11: Annual Service Charge (year 1) | B11: 1950000 | C11: GBP, CPI-indexed (input)
A12: CPI indexation | B12: 0.03 | C12: per annum (input)
A13: LTSA term | B13: 7 | C13: years from COD (input)
A14: Guaranteed Availability | B14: 0.9775 | C14: per Contract Year (input)
A15: Availability LD cap | B15: 0.1 | C15: of annual Service Charge (input)
A16: Liability cap | B16: 1.35 | C16: x trailing 12m Charges (input)
A17: Supply super-cap | B17: 17500000 | C17: GBP (input)
A18: Advance payment % | B18: 0.1 | C18: of Supply Price on signature (input)

Sheet Milestones
A1: Supply Price Milestone Schedule (executed)
A3: Milestone | B3: % of Supply Price | C3: Amount (GBP) | D3: Cumulative (GBP)
A4: Signature (advance payment) | B4: 0.1 | C4: =B4*Assumptions!$B$9 -> 6240000 | D4: =C4 -> 6240000
A5: Cells and PCS ordered | B5: 0.25 | C5: =B5*Assumptions!$B$9 -> 15600000 | D5: =D4+C5 -> 21840000
A6: Delivery to Site | B6: 0.25 | C6: =B6*Assumptions!$B$9 -> 15600000 | D6: =D5+C6 -> 37440000
A7: Mechanical completion | B7: 0.2 | C7: =B7*Assumptions!$B$9 -> 12480000 | D7: =D6+C7 -> 49920000
A8: Commercial Operation Date | B8: 0.15 | C8: =B8*Assumptions!$B$9 -> 9360000 | D8: =D7+C8 -> 59280000
A9: End of Defects Liability Period (retention) | B9: 0.05 | C9: =B9*Assumptions!$B$9 -> 3120000 | D9: =D8+C9 -> 62400000
A10: Total Supply Price | B10: =SUM(B4:B9) -> 1 | C10: =SUM(C4:C9) -> 62400000 | D10: =C10 -> 62400000

Sheet LTSA_Charges
A1: Recurring Charges over 7-year LTSA term (CPI-indexed)
A3: Contract Year | B3: Licence Fee (GBP) | C3: Service Charge (GBP) | D3: Annual recurring (GBP) | E3: Cumulative recurring (GBP) | F3: Avail. LD cap (GBP)
A4: 1 | B4: =Assumptions!$B$10 -> 840000 | C4: =Assumptions!$B$11 -> 1950000 | D4: =B4+C4 -> 2790000 | E4: =D4 -> 2790000 | F4: =C4*Assumptions!$B$15 -> 195000
A5: 2 | B5: =B4*(1+Assumptions!$B$12) -> 865200 | C5: =C4*(1+Assumptions!$B$12) -> 2008500 | D5: =B5+C5 -> 2873700 | E5: =E4+D5 -> 5663700 | F5: =C5*Assumptions!$B$15 -> 200850
A6: 3 | B6: =B5*(1+Assumptions!$B$12) -> 891156 | C6: =C5*(1+Assumptions!$B$12) -> 2068755 | D6: =B6+C6 -> 2959911 | E6: =E5+D6 -> 8623611 | F6: =C6*Assumptions!$B$15 -> 206875.5
A7: 4 | B7: =B6*(1+Assumptions!$B$12) -> 917890.68 | C7: =C6*(1+Assumptions!$B$12) -> 2130817.6 | D7: =B7+C7 -> 3048708.3 | E7: =E6+D7 -> 11672319 | F7: =C7*Assumptions!$B$15 -> 213081.77
A8: 5 | B8: =B7*(1+Assumptions!$B$12) -> 945427.4 | C8: =C7*(1+Assumptions!$B$12) -> 2194742.2 | D8: =B8+C8 -> 3140169.6 | E8: =E7+D8 -> 14812489 | F8: =C8*Assumptions!$B$15 -> 219474.22
A9: 6 | B9: =B8*(1+Assumptions!$B$12) -> 973790.22 | C9: =C8*(1+Assumptions!$B$12) -> 2260584.4 | D9: =B9+C9 -> 3234374.7 | E9: =E8+D9 -> 18046864 | F9: =C9*Assumptions!$B$15 -> 226058.44
A10: 7 | B10: =B9*(1+Assumptions!$B$12) -> 1003003.9 | C10: =C9*(1+Assumptions!$B$12) -> 2328402 | D10: =B10+C10 -> 3331405.9 | E10: =E9+D10 -> 21378269 | F10: =C10*Assumptions!$B$15 -> 232840.2
A11: Total (7 yrs) | B11: =SUM(B4:B10) -> 6436468.2 | C11: =SUM(C4:C10) -> 14941801 | D11: =SUM(D4:D10) -> 21378269 | E11: =E10 -> 21378269 | F11: =SUM(F4:F10) -> 1494180.1

Sheet ContractValue
A1: Total Contract Value summary
A3: Component | B3: Amount (GBP)
A4: Supply Price (capital) | B4: =Assumptions!B9 -> 62400000
A5: Total Licence Fees (7 yrs) | B5: =LTSA_Charges!B11 -> 6436468.2
A6: Total Service Charges (7 yrs) | B6: =LTSA_Charges!C11 -> 14941801
A7: Total Contract Value (7-yr) | B7: =SUM(B4:B6) -> 83778269
