Workbook

Sheet Assumptions
B2: PROJECT MERIDIAN — Sentvia Vigil™ Subscription
B3: Commercial Model & Total Cost of Ownership (5-year view)
B4: Whitfield Carter LLP | Matter WC-00122 | Prepared 28 January 2026
B6: Key assumptions
B7: Annual subscription (Year 1) | C7: 486000
B8: Implementation / migration fixed fee (one-off) | C8: 145000
B9: Annual uplift cap (negotiated, clause 6.6) | C9: 0.05
B10: Authorised users (Year 1) | C10: 120
B11: Additional user rate (per user p.a.) | C11: 4050
B12: Forecast additional users from Year 2 | C12: 15
B13: Premium support (24x7 P1/P2) add-on p.a. | C13: 38000
B14: Discount applied to Year 1 subscription | C14: 0.1
B15: VAT rate | C15: 0.2
B17: Note: Blue cells are inputs. Annual subscription escalates at the lesser of the negotiated cap and CPI; modelled here at the cap.

Sheet 5-Year TCO
B2: Five-Year Total Cost of Ownership
B4: Cost component | C4: Year 1 | D4: Year 2 | E4: Year 3 | F4: Year 4 | G4: Year 5 | H4: Total
B5: Platform subscription | C5: =Assumptions!$C$7*(1-Assumptions!$C$14) -> 437400 | D5: =C5*(1+Assumptions!$C$9) -> 459270 | E5: =D5*(1+Assumptions!$C$9) -> 482233.5 | F5: =E5*(1+Assumptions!$C$9) -> 506345.17 | G5: =F5*(1+Assumptions!$C$9) -> 531662.43 | H5: =SUM(C5:G5) -> 2416911.1
B6: Additional user subscriptions | C6: 0 | D6: =Assumptions!$C$12*Assumptions!$C$11*(1+Assumptions!$C$9)^0 -> 60750 | E6: =Assumptions!$C$12*Assumptions!$C$11*(1+Assumptions!$C$9)^1 -> 63787.5 | F6: =Assumptions!$C$12*Assumptions!$C$11*(1+Assumptions!$C$9)^2 -> 66976.875 | G6: =Assumptions!$C$12*Assumptions!$C$11*(1+Assumptions!$C$9)^3 -> 70325.719 | H6: =SUM(C6:G6) -> 261840.09
B7: Premium 24x7 support add-on | C7: =Assumptions!$C$13*(1+Assumptions!$C$9)^0 -> 38000 | D7: =Assumptions!$C$13*(1+Assumptions!$C$9)^1 -> 39900 | E7: =Assumptions!$C$13*(1+Assumptions!$C$9)^2 -> 41895 | F7: =Assumptions!$C$13*(1+Assumptions!$C$9)^3 -> 43989.75 | G7: =Assumptions!$C$13*(1+Assumptions!$C$9)^4 -> 46189.238 | H7: =SUM(C7:G7) -> 209973.99
B8: Implementation & migration (one-off) | C8: =Assumptions!$C$8 -> 145000 | D8: 0 | E8: 0 | F8: 0 | G8: 0 | H8: =SUM(C8:G8) -> 145000
B9: Subtotal (excl. VAT) | C9: =SUM(C5:C8) -> 620400 | D9: =SUM(D5:D8) -> 559920 | E9: =SUM(E5:E8) -> 587916 | F9: =SUM(F5:F8) -> 617311.8 | G9: =SUM(G5:G8) -> 648177.39 | H9: =SUM(C9:G9) -> 3033725.2
B10: VAT | C10: =C9*Assumptions!$C$15 -> 124080 | D10: =D9*Assumptions!$C$15 -> 111984 | E10: =E9*Assumptions!$C$15 -> 117583.2 | F10: =F9*Assumptions!$C$15 -> 123462.36 | G10: =G9*Assumptions!$C$15 -> 129635.48 | H10: =SUM(C10:G10) -> 606745.04
B11: Total (incl. VAT) | C11: =C9+C10 -> 744480 | D11: =D9+D10 -> 671904 | E11: =E9+E10 -> 705499.2 | F11: =F9+F10 -> 740774.16 | G11: =G9+G10 -> 777812.87 | H11: =SUM(C11:G11) -> 3640470.2
B13: Contract value over 36-month initial term (subscription + implementation, excl. VAT): | F13: =SUM(C5:E5)+C8 -> 1523903.5

Sheet SOW Milestones
B2: SOW-01 Implementation — Milestone Payment Schedule
B4: Ref | C4: Milestone | D4: Target date | E4: Fee (excl. VAT) | F4: VAT | G4: Total
B5: M1 | C5: Project Initiation & Implementation Plan | D5: 2025-12-15 | E5: 21750 | F5: =E5*Assumptions!$C$15 -> 4350 | G5: =E5+F5 -> 26100
B6: M2 | C6: Environments provisioned (Prod/UAT/Sandbox) | D6: 2026-01-09 | E6: 21750 | F6: =E6*Assumptions!$C$15 -> 4350 | G6: =E6+F6 -> 26100
B7: M3 | C7: Configuration complete & spec approved | D7: 2026-02-06 | E7: 29000 | F7: =E7*Assumptions!$C$15 -> 5800 | G7: =E7+F7 -> 34800
B8: M4 | C8: Data migration dry-run & reconciliation | D8: 2026-02-27 | E8: 29000 | F8: =E8*Assumptions!$C$15 -> 5800 | G8: =E8+F8 -> 34800
B9: M5 | C9: CSV / validation pack (IQ/OQ/PQ) | D9: 2026-03-13 | E9: 21750 | F9: =E9*Assumptions!$C$15 -> 4350 | G9: =E9+F9 -> 26100
B10: M6 | C10: Go-live & hypercare | D10: 2026-03-27 | E10: 21750 | F10: =E10*Assumptions!$C$15 -> 4350 | G10: =E10+F10 -> 26100
C11: TOTAL | E11: =SUM(E5:E10) -> 145000 | F11: =SUM(F5:F10) -> 29000 | G11: =SUM(G5:G10) -> 174000
