Workbook

Sheet Summary
B1: Caspian Technologies Limited — Stratton Energy plc
B2: Enterprise SaaS Pricing Model — Caspian Climate Intelligence Platform
B3: Matter WC-00109 | Prepared 8 May 2026 | Strictly subject to contract
B5: Metric | C5: Value
B6: Annual Subscription Fee (Year 1) | C6: =Assumptions!$C$6 -> 450000
B7: Annual uplift | C7: =Assumptions!$C$7 -> 0.05
B8: Implementation & Onboarding Fee | C8: =Assumptions!$C$8 -> 85000
B9: Professional services rate (per day) | C9: =Assumptions!$C$9 -> 1250
B10: Estimated PS days (Year 1) | C10: =Assumptions!$C$10 -> 40
B11: Total Year-1 charges (ex VAT) | C11: =Assumptions!$C$6+Assumptions!$C$8+Assumptions!$C$9*Assumptions!$C$10 -> 585000
B12: 3-year subscription total | C12: ='Subscription Schedule'!$E$9 -> 1418625
B13: Total Contract Value (TCV) | C13: ='TCV Build'!$C$9 -> 1553625

Sheet Assumptions
B1: Caspian Technologies Limited — Stratton Energy plc
B2: Enterprise SaaS Pricing Model — Caspian Climate Intelligence Platform
B3: Matter WC-00109 | Prepared 8 May 2026 | Strictly subject to contract
B5: Input | C5: Value | D5: Notes
B6: Annual Subscription Fee (Year 1) | C6: 450000 | D6: Enterprise tier; per heads of terms
B7: Annual uplift | C7: 0.05 | D7: Applied on each Go-Live anniversary
B8: Implementation & Onboarding Fee (one-off) | C8: 85000 | D8: Invoiced on signature
B9: Professional services rate (per day) | C9: 1250 | D9: Drawn down under work orders
B10: Estimated PS days (Year 1) | C10: 40 | D10: Estimate, not a commitment
B11: Authorised Users (max) | C11: 250 | D11: Named users
B12: Initial Term (months) | C12: 36 | D12: From Go-Live (target 1 Jul 2026)
B13: Payment terms (days) | C13: 45 | D13: Annually in advance
B14: Liability cap (% of trailing 12m Fees) | C14: 1.5 | D14: Carve-outs uncapped
B15: Target monthly availability | C15: 0.998 | D15: Service Level (SLA Schedule 2)
B16: VAT rate | C16: 0.2 | D16: Added on invoicing; excluded from TCV

Sheet Subscription Schedule
B1: Caspian Technologies Limited — Stratton Energy plc
B2: Enterprise SaaS Pricing Model — Caspian Climate Intelligence Platform
B3: Matter WC-00109 | Prepared 8 May 2026 | Strictly subject to contract
B5: Year | C5: Period | D5: Uplift applied | E5: Subscription Fee | F5: Cumulative
B6: 1 | C6: Go-Live + 0–12m | D6: — | E6: =Assumptions!$C$6 -> 450000 | F6: =E6 -> 450000
B7: 2 | C7: Go-Live + 12–24m | D7: =Assumptions!$C$7 -> 0.05 | E7: =E6*(1+Assumptions!$C$7) -> 472500 | F7: =F6+E7 -> 922500
B8: 3 | C8: Go-Live + 24–36m | D8: =Assumptions!$C$7 -> 0.05 | E8: =E7*(1+Assumptions!$C$7) -> 496125 | F8: =F7+E8 -> 1418625
B9: 3-year subscription total | E9: =SUM(E6:E8) -> 1418625 | F9: =E9 -> 1418625

Sheet TCV Build
B1: Caspian Technologies Limited — Stratton Energy plc
B2: Enterprise SaaS Pricing Model — Caspian Climate Intelligence Platform
B3: Matter WC-00109 | Prepared 8 May 2026 | Strictly subject to contract
B5: Component | C5: Amount | D5: Notes
B6: 3-year subscription | C6: ='Subscription Schedule'!$E$9 -> 1418625 | D6: Years 1–3, 5% annual uplift
B7: Implementation & onboarding | C7: =Assumptions!$C$8 -> 85000 | D7: One-off, on signature
B8: Professional services (Year 1 est.) | C8: =Assumptions!$C$9*Assumptions!$C$10 -> 50000 | D8: 40 days @ £1,250
B9: Total Contract Value (TCV) | C9: =SUM(C6:C8) -> 1553625 | D9: Subscription + implementation + Year-1 PS
B11: Year-1 charges (for first-year budgeting)
B12: Subscription (Year 1) | C12: =Assumptions!$C$6 -> 450000
B13: Implementation & onboarding | C13: =Assumptions!$C$8 -> 85000
B14: Professional services (Year 1 est.) | C14: =Assumptions!$C$9*Assumptions!$C$10 -> 50000
B15: Total Year-1 charges (ex VAT) | C15: =SUM(C12:C14) -> 585000
B16: Total Year-1 charges (inc VAT @ 20%) | C16: =C15*(1+Assumptions!$C$16) -> 702000

Sheet Invoicing Schedule
B1: Caspian Technologies Limited — Stratton Energy plc
B2: Enterprise SaaS Pricing Model — Caspian Climate Intelligence Platform
B3: Matter WC-00109 | Prepared 8 May 2026 | Strictly subject to contract
B5: Invoice date | C5: Description | D5: Net (£) | E5: VAT (£) | F5: Gross (£) | G5: Due (45d)
B6: 01 Jul 2026 | C6: Implementation & onboarding (one-off) | D6: =Assumptions!$C$8 -> 85000 | E6: =D6*Assumptions!$C$16 -> 17000 | F6: =D6+E6 -> 102000 | G6: 15 Aug 2026
B7: 01 Jul 2026 | C7: Annual subscription — Year 1 | D7: =Assumptions!$C$6 -> 450000 | E7: =D7*Assumptions!$C$16 -> 90000 | F7: =D7+E7 -> 540000 | G7: 15 Aug 2026
B8: 31 Mar 2027 | C8: Professional services — Year 1 (estimate) | D8: =Assumptions!$C$9*Assumptions!$C$10 -> 50000 | E8: =D8*Assumptions!$C$16 -> 10000 | F8: =D8+E8 -> 60000 | G8: 15 May 2027
B9: 01 Jul 2027 | C9: Annual subscription — Year 2 | D9: ='Subscription Schedule'!$E$7 -> 472500 | E9: =D9*Assumptions!$C$16 -> 94500 | F9: =D9+E9 -> 567000 | G9: 15 Aug 2027
B10: 01 Jul 2028 | C10: Annual subscription — Year 3 | D10: ='Subscription Schedule'!$E$8 -> 496125 | E10: =D10*Assumptions!$C$16 -> 99225 | F10: =D10+E10 -> 595350 | G10: 15 Aug 2028
C11: Total over Initial Term | D11: =SUM(D6:D10) -> 1553625 | E11: =SUM(E6:E10) -> 310725 | F11: =SUM(F6:F10) -> 1864350
C12: Net total ex-VAT ties to TCV | D12: =D11-'TCV Build'!$C$9 -> 0 | E12: check (=0)

Sheet Scenarios
B1: Caspian Technologies Limited — Stratton Energy plc
B2: Enterprise SaaS Pricing Model — Caspian Climate Intelligence Platform
B3: Matter WC-00109 | Prepared 8 May 2026 | Strictly subject to contract
B5: TCV sensitivity to annual uplift and Year-1 subscription
B7: Uplift \ Year-1 sub | C7: £420,000 | D7: £450,000 | E7: £480,000
B8: 0.03 | C8: =420000*(1+(1+0.03)+(1+0.03)^2)+Assumptions!$C$8+Assumptions!$C$9*Assumptions!$C$10 -> 1433178 | D8: =450000*(1+(1+0.03)+(1+0.03)^2)+Assumptions!$C$8+Assumptions!$C$9*Assumptions!$C$10 -> 1525905 | E8: =480000*(1+(1+0.03)+(1+0.03)^2)+Assumptions!$C$8+Assumptions!$C$9*Assumptions!$C$10 -> 1618632
B9: 0.05 | C9: =420000*(1+(1+0.05)+(1+0.05)^2)+Assumptions!$C$8+Assumptions!$C$9*Assumptions!$C$10 -> 1459050 | D9: =450000*(1+(1+0.05)+(1+0.05)^2)+Assumptions!$C$8+Assumptions!$C$9*Assumptions!$C$10 -> 1553625 | E9: =480000*(1+(1+0.05)+(1+0.05)^2)+Assumptions!$C$8+Assumptions!$C$9*Assumptions!$C$10 -> 1648200
B10: 0.07 | C10: =420000*(1+(1+0.07)+(1+0.07)^2)+Assumptions!$C$8+Assumptions!$C$9*Assumptions!$C$10 -> 1485258 | D10: =450000*(1+(1+0.07)+(1+0.07)^2)+Assumptions!$C$8+Assumptions!$C$9*Assumptions!$C$10 -> 1581705 | E10: =480000*(1+(1+0.07)+(1+0.07)^2)+Assumptions!$C$8+Assumptions!$C$9*Assumptions!$C$10 -> 1678152
B12: Base case (5% uplift, £450,000) shown in centre cell; ties to TCV Build.
