Workbook

Sheet Assumptions
A1: Calderwater Utilities Limited — Master Manufacture & Supply Agreement
A2: Schedule 3 — Pricing & Volume Model (Project Aquilo, WC-00167)
A3: Prepared by Whitfield Carter LLP for Harrow Precision Engineering Limited. Blue cells = inputs.
A5: Key commercial assumptions
A6: Term (years) | B6: 5 | C6: Initial Term (clause 2.2)
A7: Minimum Commitment per Contract Year (£ ex VAT) | B7: 3500000 | C7: Clause 6.1
A8: Shortfall payment rate (% of shortfall) | B8: 0.08 | C8: Clause 6.2 (negotiated from 15%)
A9: Estimated annual spend (£ ex VAT) | B9: 4200000 | C9: Heads of Terms para 5 — indicative
A10: CPI indexation assumption (% p.a.) | B10: 0.035 | C10: Forecast CPI
A11: CPI indexation cap (% p.a.) | B11: 0.04 | C11: Clause 7.2 — cap
A12: Payment terms (days) | B12: 45 | C12: Clause 8.1
A13: Warranty (months) | B13: 24 | C13: Clause 9.1
A14: Liability cap (£ aggregate) | B14: 4000000 | C14: Clause 11.3
A15: IP indemnity sub-cap (£) | B15: 5000000 | C15: Clause 11.3

Sheet Year1_PriceList
A1: Schedule 3 — Year 1 Unit Prices (fixed for Contract Year 1; £ ex VAT)
A3: Ref | B3: Description | C3: Unit | D3: List price (£) | E3: Framework discount % | F3: Contract unit price (£)
A4: HX-200 | B4: Dry-well centrifugal pump set, 200mm, 37 kW | C4: each | D4: 18500 | E4: 0.1 | F4: =D4*(1-E4) -> 16650
A5: HX-300 | B5: Dry-well centrifugal pump set, 300mm, 90 kW | C5: each | D5: 41200 | E5: 0.1 | F5: =D5*(1-E5) -> 37080
A6: SX-150 | B6: Submersible wastewater pump, 150mm, 11 kW | C6: each | D6: 7400 | E6: 0.12 | F6: =D6*(1-E6) -> 6512
A7: SX-250 | B7: Submersible wastewater pump, 250mm, 30 kW | C7: each | D7: 15800 | E7: 0.12 | F7: =D7*(1-E7) -> 13904
A8: CP-STD | B8: Motor control panel, IP54, soft-start, telemetry | C8: each | D8: 9600 | E8: 0.08 | F8: =D8*(1-E8) -> 8832
A9: SP-SEAL | B9: Mechanical seal kit (SiC/SiC double) | C9: kit | D9: 640 | E9: 0.05 | F9: =D9*(1-E9) -> 608
A10: SP-IMP-HX | B10: Replacement impeller, HX range (duplex SS) | C10: each | D10: 2850 | E10: 0.05 | F10: =D10*(1-E10) -> 2707.5
A11: SP-IMP-SX | B11: Replacement impeller, SX range | C11: each | D11: 1180 | E11: 0.05 | F11: =D11*(1-E11) -> 1121
A12: SVC-COMM | B12: Commissioning visit (per pump set) | C12: visit | D12: 950 | E12: 0 | F12: =D12*(1-E12) -> 950
A13: SVC-PM | B13: Planned-maintenance visit (per set) | C13: visit | D13: 480 | E13: 0 | F13: =D13*(1-E13) -> 480

Sheet Year1_VolumePlan
A1: Indicative Year 1 Order Plan (not a commitment per item; ties to Minimum Commitment)
A3: Ref | B3: Description | C3: Indicative qty | D3: Contract unit price (£) | E3: Line value (£)
A4: HX-200 | B4: Dry-well centrifugal pump set, 200mm, 37 kW | C4: 58 | D4: =Year1_PriceList!F4 -> 16650 | E4: =C4*D4 -> 965700
A5: HX-300 | B5: Dry-well centrifugal pump set, 300mm, 90 kW | C5: 26 | D5: =Year1_PriceList!F5 -> 37080 | E5: =C5*D5 -> 964080
A6: SX-150 | B6: Submersible wastewater pump, 150mm, 11 kW | C6: 80 | D6: =Year1_PriceList!F6 -> 6512 | E6: =C6*D6 -> 520960
A7: SX-250 | B7: Submersible wastewater pump, 250mm, 30 kW | C7: 48 | D7: =Year1_PriceList!F7 -> 13904 | E7: =C7*D7 -> 667392
A8: CP-STD | B8: Motor control panel, IP54, soft-start, telemetry | C8: 76 | D8: =Year1_PriceList!F8 -> 8832 | E8: =C8*D8 -> 671232
A9: SP-SEAL | B9: Mechanical seal kit (SiC/SiC double) | C9: 160 | D9: =Year1_PriceList!F9 -> 608 | E9: =C9*D9 -> 97280
A10: SP-IMP-HX | B10: Replacement impeller, HX range (duplex SS) | C10: 34 | D10: =Year1_PriceList!F10 -> 2707.5 | E10: =C10*D10 -> 92055
A11: SP-IMP-SX | B11: Replacement impeller, SX range | C11: 55 | D11: =Year1_PriceList!F11 -> 1121 | E11: =C11*D11 -> 61655
A12: SVC-COMM | B12: Commissioning visit (per pump set) | C12: 120 | D12: =Year1_PriceList!F12 -> 950 | E12: =C12*D12 -> 114000
A13: SVC-PM | B13: Planned-maintenance visit (per set) | C13: 190 | D13: =Year1_PriceList!F13 -> 480 | E13: =C13*D13 -> 91200
B14: Total indicative Year 1 order value (£ ex VAT) | E14: =SUM(E4:E13) -> 4245554
B16: Minimum Commitment (clause 6.1) | E16: =Assumptions!$B$7 -> 3500000
B17: Headroom over Minimum Commitment | E17: =E14-E16 -> 745554
B19: Illustrative shortfall if only Minimum Commitment value ordered:
B20: Shortfall payment if Year 1 orders = £2,800,000 (example) | D20: 2800000 | E20: =MAX(0,(Assumptions!$B$7-D20)*Assumptions!$B$8) -> 56000

Sheet 5yr_Projection
A1: 5-Year Spend Projection with CPI Indexation (capped at 4% p.a., clause 7.2)
A3: Contract Year | B3: Indexation applied % | C3: Price index (Yr1=1.000) | D3: Projected order value (£) | E3: Minimum Commitment (£) | F3: Meets minimum?
A4: Year 1 | B4: 0 | C4: 1 | D4: =Year1_VolumePlan!$E$14*C4 -> 4245554 | E4: =Assumptions!$B$7 -> 3500000 | F4: =IF(D4>=E4,"Yes","No") -> Yes
A5: Year 2 | B5: =MIN(Assumptions!$B$10,Assumptions!$B$11) -> 0.035 | C5: =C4*(1+B5) -> 1.035 | D5: =Year1_VolumePlan!$E$14*C5 -> 4394148.4 | E5: =Assumptions!$B$7 -> 3500000 | F5: =IF(D5>=E5,"Yes","No") -> Yes
A6: Year 3 | B6: =MIN(Assumptions!$B$10,Assumptions!$B$11) -> 0.035 | C6: =C5*(1+B6) -> 1.071225 | D6: =Year1_VolumePlan!$E$14*C6 -> 4547943.6 | E6: =Assumptions!$B$7 -> 3500000 | F6: =IF(D6>=E6,"Yes","No") -> Yes
A7: Year 4 | B7: =MIN(Assumptions!$B$10,Assumptions!$B$11) -> 0.035 | C7: =C6*(1+B7) -> 1.1087179 | D7: =Year1_VolumePlan!$E$14*C7 -> 4707121.6 | E7: =Assumptions!$B$7 -> 3500000 | F7: =IF(D7>=E7,"Yes","No") -> Yes
A8: Year 5 | B8: =MIN(Assumptions!$B$10,Assumptions!$B$11) -> 0.035 | C8: =C7*(1+B8) -> 1.147523 | D8: =Year1_VolumePlan!$E$14*C8 -> 4871870.9 | E8: =Assumptions!$B$7 -> 3500000 | F8: =IF(D8>=E8,"Yes","No") -> Yes
A9: 5-year total (projected) | D9: =SUM(D4:D8) -> 22766638 | E9: =SUM(E4:E8) -> 17500000
