Workbook

Sheet Assumptions
A1: Project Cedar — Pricing & Contract Value Model
A2: Halstead Aerospace Limited / Caldera Mobility Systems plc — CM-7 composite airframe supply
A3: Prepared by Whitfield Carter LLP (WC-00131) — figures exclusive of VAT
A5: Key commercial assumptions
A6: Year-1 list unit price per shipset | B6: 148500
A7: Non-recurring engineering & tooling (NRE) | B7: 2400000
A8: Year-1 minimum commitment (shipsets) | B8: 60
A9: Volume discount — tier 2 (41–80 / yr) | B9: 0.05
A10: Volume discount — tier 3 (81–120 / yr) | B10: 0.1
A11: Volume discount — tier 4 (121+ / yr) | B11: 0.15
A12: Annual indexation factor (of PPI change) | B12: 0.7
A13: Assumed annual PPI change | B13: 0.03
A14: Indexation cap (±) | B14: 0.04
A15: Late-delivery LD rate (per week) | B15: 0.005
A16: Late-delivery LD cap | B16: 0.075
A17: Payment terms (days) | B17: 60
A18: Liability cap (% trailing 12m charges) | B18: 1.25
A30: Cells: B6=list price, B8=Yr1 min, B7=NRE

Sheet VolumePricing
A1: Schedule 2 — Volume Pricing (Year 1)
A3: Tier | B3: Annual volume (shipsets) | C3: Discount | D3: Unit price per shipset | E3: Notes
A4: Tier 1 | B4: 1 – 40 | C4: 0 | D4: =Assumptions!$B$6*(1-C4) | E4: Standard list
A5: Tier 2 | B5: 41 – 80 | C5: 0.05 | D5: =Assumptions!$B$6*(1-C5) | E5: Applies to Yr-1 commitment of 60
A6: Tier 3 | B6: 81 – 120 | C6: 0.1 | D6: =Assumptions!$B$6*(1-C6) | E6: Series ramp
A7: Tier 4 | B7: 121+ | C7: 0.15 | D7: =Assumptions!$B$6*(1-C7) | E7: Mature rate

Sheet ContractValue
A1: Five-Year Contract Value (illustrative ramp)
A3: Contract year | B3: Shipsets | C3: Applicable tier discount | D3: Indexation uplift | E3: Effective unit price | F3: Product revenue | G3: NRE / tooling | H3: Total year value
A4: Year 1 | B4: 60 | C4: 0.05 | D4: =(1+MIN(Assumptions!$B$13,Assumptions!$B$11*Assumptions!$B$12))^0 | E4: =Assumptions!$B$6*(1-C4)*D4 | F4: =B4*E4 | G4: =Assumptions!$B$7 | H4: =F4+G4
A5: Year 2 | B5: 84 | C5: 0.1 | D5: =(1+MIN(Assumptions!$B$13,Assumptions!$B$11*Assumptions!$B$12))^1 | E5: =Assumptions!$B$6*(1-C5)*D5 | F5: =B5*E5 | G5: 0 | H5: =F5+G5
A6: Year 3 | B6: 108 | C6: 0.1 | D6: =(1+MIN(Assumptions!$B$13,Assumptions!$B$11*Assumptions!$B$12))^2 | E6: =Assumptions!$B$6*(1-C6)*D6 | F6: =B6*E6 | G6: 0 | H6: =F6+G6
A7: Year 4 | B7: 132 | C7: 0.15 | D7: =(1+MIN(Assumptions!$B$13,Assumptions!$B$11*Assumptions!$B$12))^3 | E7: =Assumptions!$B$6*(1-C7)*D7 | F7: =B7*E7 | G7: 0 | H7: =F7+G7
A8: Year 5 | B8: 156 | C8: 0.15 | D8: =(1+MIN(Assumptions!$B$13,Assumptions!$B$11*Assumptions!$B$12))^4 | E8: =Assumptions!$B$6*(1-C8)*D8 | F8: =B8*E8 | G8: 0 | H8: =F8+G8
A9: TOTAL | B9: =SUM(B4:B8) | F9: =SUM(F4:F8) | G9: =SUM(G4:G8) | H9: =SUM(H4:H8)
A11: Year-1 gross list value (60 shipsets @ list £148,500): | F11: =Assumptions!$B$8*Assumptions!$B$6
A12: Year-1 product revenue (60 shipsets @ tier-2 discount): | F12: =F4
A13: Total Year-1 value incl. NRE: | F13: =H4

Sheet NRE_Schedule
A1: NRE / Tooling Milestone Payment Schedule
A3: Milestone | B3: Trigger | C3: Target date | D3: % of NRE | E3: Amount (£)
A4: M1 | B4: Signature of MSA | C4: 05-Dec-2025 | D4: 0.4 | E4: =Assumptions!$B$7*D4
A5: M3 | B5: First-article inspection accepted | C5: 15-May-2026 | D5: 0.3 | E5: =Assumptions!$B$7*D5
A6: M4 | B6: Tooling qualification complete | C6: 30-Jun-2026 | D6: 0.3 | E6: =Assumptions!$B$7*D6
A7: TOTAL | D7: =SUM(D4:D6) | E7: =SUM(E4:E6)
